COPYING
MANIFEST.in
README.md
RELEASE-VERSION
SConstruct
pavement.py
paver-minilib.zip
setup.py
version.py
motor_control/__init__.py
motor_control/config.py
motor_control/node.py
motor_control/proxy.py
motor_control/Arduino/motor_control/Node.cpp
motor_control/Arduino/motor_control/Node.h
motor_control/Arduino/motor_control/NodeCommandProcessor.h
motor_control/Arduino/motor_control/RPCBuffer.h
motor_control/Arduino/motor_control/RPCBuffer.ht
motor_control/Arduino/motor_control/SConscript
motor_control/Arduino/motor_control/config.options
motor_control/Arduino/motor_control/config.proto
motor_control/Arduino/motor_control/motor_control.ino
motor_control/Arduino/motor_control/motor_control_config_pb.c
motor_control/Arduino/motor_control/motor_control_config_pb.h
motor_control/Arduino/motor_control/motor_control_config_validate.h
motor_control/Arduino/motor_control/motor_control_state_validate.h
motor_control/Arduino/motor_control/TimerOne/README.md
motor_control/Arduino/motor_control/TimerOne/TimerOne.cpp
motor_control/Arduino/motor_control/TimerOne/TimerOne.h
motor_control/Arduino/motor_control/TimerOne/keywords.txt
motor_control/Arduino/motor_control/TimerOne/library.json
motor_control/Arduino/motor_control/TimerOne/library.properties
motor_control/Arduino/motor_control/TimerOne/.git/HEAD
motor_control/Arduino/motor_control/TimerOne/.git/config
motor_control/Arduino/motor_control/TimerOne/.git/description
motor_control/Arduino/motor_control/TimerOne/.git/index
motor_control/Arduino/motor_control/TimerOne/.git/packed-refs
motor_control/Arduino/motor_control/TimerOne/.git/hooks/applypatch-msg.sample
motor_control/Arduino/motor_control/TimerOne/.git/hooks/commit-msg.sample
motor_control/Arduino/motor_control/TimerOne/.git/hooks/post-update.sample
motor_control/Arduino/motor_control/TimerOne/.git/hooks/pre-applypatch.sample
motor_control/Arduino/motor_control/TimerOne/.git/hooks/pre-commit.sample
motor_control/Arduino/motor_control/TimerOne/.git/hooks/pre-push.sample
wheeler.motor_control.egg-info/PKG-INFO
wheeler.motor_control.egg-info/SOURCES.txt
wheeler.motor_control.egg-info/dependency_links.txt
wheeler.motor_control.egg-info/requires.txt
wheeler.motor_control.egg-info/top_level.txt