Metadata-Version: 1.0
Name: wheeler.motor-control
Version: 0.2.post2
Summary: Arduino RPC node packaged as Python package.
Home-page: http://github.com/wheeler-microfluidics/motor-control.git
Author: Christian Fobel
Author-email: christian@fobel.net
License: GPLv2
Platform: UNKNOWN
